prompt_horizon/__init__.py
prompt_horizon/anonymizer.py
prompt_horizon/de_anonymizer.py
prompthorizon/__init__.py
prompthorizon/anonymizer.py
prompthorizon/de_anonymizer.py
tests/__init__.py
tests/test_anonymizer.py
tests/test_anonymizer_complex.py
tests/test_de_anonymizer.py
prompt_horizon-0.1.4.dist-info/LICENSE
prompt_horizon-0.1.4.dist-info/METADATA
prompt_horizon-0.1.4.dist-info/WHEEL
prompt_horizon-0.1.4.dist-info/top_level.txt
prompt_horizon-0.1.4.dist-info/RECORD
