Metadata-Version: 2.1
Name: prompt-horizon
Version: 0.1.4
Summary: Library to anonymize JSON objects by creating placeholders for keys and values, while generating a reversible mapping to restore afterwards
Home-page: https://github.com/gkanellopoulos/prompthorizon.git
Author: George Kanellopoulos
Author-email: george@gkanellopoulos.com
Classifier: Development Status :: 3 - Alpha
Classifier: Intended Audience :: Developers
Classifier: License :: OSI Approved :: MIT License
Classifier: Programming Language :: Python :: 3
Classifier: Programming Language :: Python :: 3.6
Classifier: Programming Language :: Python :: 3.7
Classifier: Programming Language :: Python :: 3.8
Classifier: Programming Language :: Python :: 3.9
License-File: LICENSE
